[
    {
        "id": 1,
        "name": "Charly'",
        "nameU": "charly01",
        "email": "Charly@gmail.com",
        "password": "$2b$10$d4cktEoGB7NuBp8jMj2pUe23gBtsnsUgd6zaTkgicY.wfhrcc4mvK",
        "admin": true,
        "image": "image1600115680678.jpg"
    },
    {
        "id": 2,
        "name": "pepe",
        "nameU": "pepin",
        "email": "pepe@gmail.com",
        "password": "$2b$10$W9fTFjz1ykEn8b1V/pz1YOdXJP2qNP.4fEIt2W35vjRshmmsdqTy6",
        "image": "image1600115775642.png",
        "admin": true
    },
    {
        "id": 3,
        "name": "angel",
        "nameU": "angel",
        "email": "angel@gmail.com",
        "password": "$2b$10$hyiGst8VyFclgKWz3VzCf.owV7CTlfET5NSPbC5Nv1oHvMhrBuOze",
        "admin": true,
        "image": "image1600133933864.jpg"
    },
    {
        "id": 4,
        "name": "Braian",
        "nameU": "Brallam",
        "email": "Braianifernandez87@hotmail.com",
        "password": "$2b$10$z.yYYJdaTBMQTFvnaE5maO/cq7sIIZASk2wxcRZKP18C4F3iHK8vq",
        "admin": true,
        "image": "image1600226753679.jpg"
    },
    {
        "id": 5,
        "name": "jhasgdahsad",
        "nameU": "kajdgadhjnsad",
        "email": "hola@gmail.com",
        "password": "$2b$10$ndP6w1HGTLzJJwoKe./21uuqzv7DJ8wMmXLUxv/dXZwBseixB6DIa",
        "image": "default-image.png",
        "admin": false
    },
    {
        "id": 6,
        "name": "carl",
        "nameU": "carl01",
        "email": "earl@gmail.com",
        "password": "$2b$10$rgqCwqbE6rDL.sGvUoED8.sPeOC.Jz5WrXKn2ukzqp79hxHx7E2My",
        "image": "default-image.png",
        "admin": false
    },
    {
        "id": 7,
        "name": "carl",
        "nameU": "carl01",
        "email": "eeee1@gmail.com",
        "password": "$2b$10$1urcMQV3Uspk3p42kBrTseWs1E8YAuPdBGfD2moDjy0w7Hw5trcdW",
        "image": "default-image.png",
        "admin": false
    },
    {
        "id": 8,
        "name": "carl",
        "nameU": "carl02",
        "email": "elias_2006354@hotmail.com",
        "password": "$2b$10$xqlg/2GJgyx.2DM3xq24cevoDU3knB.dqv9Of40RlSv2q6VbowHfO",
        "image": "default-image.png",
        "admin": false
    },
    {
        "id": 9,
        "name": "carl",
        "nameU": "carl02",
        "email": "rr@gmail.com",
        "password": "$2b$10$zsVWRW9N4H2.gMrC3JObR.jRiemYGKgDrGPfGkwOlnGRzaCga15gG",
        "image": "default-image.png",
        "admin": false
    },
    {
        "id": 10,
        "name": "carl",
        "nameU": "carl01",
        "email": "ee@gmail.com",
        "password": "$2b$10$LN6ft63apxUZ7uGqwvyrQOIHhUx7tc1UI54to/b66jNykCwB9GYFq",
        "admin": false,
        "image": "image1600977008183.jpg"
    }
]